{
    "fluentMethods": true,
    "clientRootFolder": "microservicedaccam",
    "relationships": [],
    "fields": [
        {
            "fieldName": "libelle",
            "fieldType": "String",
            "fieldValidateRules": [
                "required"
            ]
        }
    ],
    "changelogDate": "20200602193551",
    "dto": "mapstruct",
    "searchEngine": false,
    "service": "serviceClass",
    "entityTableName": "type_caution",
    "databaseType": "sql",
    "jpaMetamodelFiltering": false,
    "pagination": "pagination",
    "microserviceName": "microservicedaccam"
}
